LICENSE
autoutils/__init__.py
autoutils/api.py
autoutils/file.py
autoutils/script.py
autoutils/thread.py
autoutils-1.0.0.dist-info/LICENSE
autoutils-1.0.0.dist-info/METADATA
autoutils-1.0.0.dist-info/WHEEL
autoutils-1.0.0.dist-info/RECORD
